cryptologic.py
cryptologic-1.0.2.dist-info/LICENSE
cryptologic-1.0.2.dist-info/WHEEL
cryptologic-1.0.2.dist-info/METADATA
cryptologic-1.0.2.dist-info/RECORD
