Metadata-Version: 2.1
Name: cryptologic
Version: 1.0.2
Summary: Python wrapper for cryptocompare API
Home-page: https://github.com/secretum-inc/cryptologic
Author: Gerrishon Sirere
Author-email: secretum.inc@pm.me
Requires-Python: >=3.6
Classifier: Intended Audience :: Information Technology
Classifier: Intended Audience :: System Administrators
Classifier: Operating System :: OS Independent
Classifier: Programming Language :: Python :: 3
Classifier: Programming Language :: Python
Classifier: Topic :: Software Development :: Libraries :: Application Frameworks
Classifier: Topic :: Software Development :: Libraries :: Python Modules
Classifier: Topic :: Software Development :: Libraries
Classifier: Topic :: Software Development
Classifier: Environment :: Web Environment
Classifier: Framework :: AsyncIO
Classifier: Development Status :: 4 - Beta
Classifier: Intended Audience :: Developers
Classifier: Programming Language :: Python :: 3 :: Only
Classifier: Programming Language :: Python :: 3.7
Classifier: Programming Language :: Python :: 3.8
Classifier: Programming Language :: Python :: 3.9
Classifier: License :: OSI Approved :: MIT License
Classifier: Topic :: Internet :: WWW/HTTP :: HTTP Servers
Classifier: Topic :: Internet :: WWW/HTTP
Requires-Dist: requests >=2.24.0,<3.0.0 ; extra == "all"
Requires-Dist: astroid==2.4.2 ; extra == "all"
Requires-Dist: attrs==20.3.0 ; extra == "all"
Requires-Dist: quo==2021.1 ; extra == "all"
Requires-Dist: autopep8==1.5.4 ; extra == "all"
Requires-Dist: certifi==2020.12.5 ; extra == "all"
Requires-Dist: chardet==4.0.0 ; extra == "all"
Requires-Dist: coveralls==3.0.0 ; extra == "all"
Requires-Dist: doc8==0.8.1 ; extra == "all"
Requires-Dist: docopt==0.6.2 ; extra == "all"
Requires-Dist: docutils==0.16 ; extra == "all"
Requires-Dist: filelock==3.0.12 ; extra == "all"
Requires-Dist: idna==2.10 ; extra == "all"
Requires-Dist: iniconfig==1.1.1 ; extra == "all"
Requires-Dist: isort==5.7.0 ; extra == "all"
Requires-Dist: lazy-object-proxy==1.4.3 ; extra == "all"
Requires-Dist: mccabe==0.6.1 ; extra == "all"
Requires-Dist: more-itertools==8.6.0 ; extra == "all"
Requires-Dist: mypy==0.800 ; extra == "all"
Requires-Dist: mypy-extensions==0.4.3 ; extra == "all"
Requires-Dist: packaging==20.8 ; extra == "all"
Requires-Dist: pbr==5.5.1 ; extra == "all"
Requires-Dist: pluggy==0.13.1 ; extra == "all"
Requires-Dist: public==2020.12.3 ; extra == "all"
Requires-Dist: py==1.10.0 ; extra == "all"
Requires-Dist: pycodestyle==2.6.0 ; extra == "all"
Requires-Dist: Pygments==2.7.4 ; extra == "all"
Requires-Dist: pylint==2.6.0 ; extra == "all"
Requires-Dist: pyparsing==2.4.7 ; extra == "all"
Requires-Dist: pytest==6.2.1 ; extra == "all"
Requires-Dist: pytest-cov==2.11.1 ; extra == "all"
Requires-Dist: pytest-mypy==0.8.0 ; extra == "all"
Requires-Dist: query-string==2020.12.3 ; extra == "all"
Requires-Dist: requests==2.25.1 ; extra == "all"
Requires-Dist: restructuredtext-lint==1.3.2 ; extra == "all"
Requires-Dist: six==1.15.0 ; extra == "all"
Requires-Dist: stevedore==3.3.0 ; extra == "all"
Requires-Dist: toml==0.10.2 ; extra == "all"
Requires-Dist: typed-ast==1.4.2 ; extra == "all"
Requires-Dist: typing-extensions==3.7.4.3 ; extra == "all"
Requires-Dist: urllib3==1.26.5 ; extra == "all"
Requires-Dist: wcwidth==0.2.5 ; extra == "all"
Requires-Dist: wrapt==1.12.1 ; extra == "all"
Project-URL: Documentation, https://github.com/secretum-inc/cryptologic
Provides-Extra: all
Provides-Extra: dev
Provides-Extra: doc
Provides-Extra: test
